mcp_server_oracle/__init__.py
mcp_server_oracle/oracle_tools.py
mcp_server_oracle-1.0.1.dist-info/METADATA
mcp_server_oracle-1.0.1.dist-info/WHEEL
mcp_server_oracle-1.0.1.dist-info/entry_points.txt
mcp_server_oracle-1.0.1.dist-info/licenses/LICENSE
mcp_server_oracle-1.0.1.dist-info/RECORD
